pybitds/__init__.py
pybitds/tools.py
pybitds-0.0.1.dist-info/METADATA
pybitds-0.0.1.dist-info/WHEEL
pybitds-0.0.1.dist-info/top_level.txt
pybitds-0.0.1.dist-info/RECORD
